codewithgpu/__init__.py
codewithgpu/cli.py
codewithgpu/version.py
codewithgpu/data/__init__.py
codewithgpu/data/dataset.py
codewithgpu/data/reader.py
codewithgpu/data/record.proto
codewithgpu/data/record.py
codewithgpu/data/record_pb2.py
codewithgpu/data/tf_record.proto
codewithgpu/data/tf_record.py
codewithgpu/data/tf_record_pb2.py
codewithgpu/inference/__init__.py
codewithgpu/inference/command.py
codewithgpu/inference/module.py
codewithgpu/model/__init__.py
codewithgpu/model/download.py
codewithgpu/model/upload.py
codewithgpu/utils/__init__.py
codewithgpu/utils/cg_cli.py
codewithgpu/utils/decorator.py
codewithgpu/utils/deprecation.py
codewithgpu/utils/logging.py
codewithgpu/utils/unittest_util.py
codewithgpu-0.2.8.dist-info/LICENSE
codewithgpu-0.2.8.dist-info/METADATA
codewithgpu-0.2.8.dist-info/WHEEL
codewithgpu-0.2.8.dist-info/entry_points.txt
codewithgpu-0.2.8.dist-info/top_level.txt
codewithgpu-0.2.8.dist-info/RECORD
